doapetry.py
doapetry-0.1.1.dist-info/METADATA
doapetry-0.1.1.dist-info/WHEEL
doapetry-0.1.1.dist-info/entry_points.txt
doapetry-0.1.1.dist-info/RECORD
