Metadata-Version: 2.3
Name: doapetry
Version: 0.1.1
Summary: Create a DOAP based on the pyproject.toml
License: EUPL-1.2
Author: Natanael Arndt
Author-email: arndtn@gmail.com
Requires-Python: >=3.9,<4.0.0
Classifier: License :: OSI Approved :: European Union Public Licence 1.2 (EUPL 1.2)
Classifier: Programming Language :: Python :: 3
Classifier: Programming Language :: Python :: 3.9
Classifier: Programming Language :: Python :: 3.10
Classifier: Programming Language :: Python :: 3.11
Classifier: Programming Language :: Python :: 3.12
Classifier: Programming Language :: Python :: 3.13
Requires-Dist: loguru (>=0.7.3,<0.8.0)
Requires-Dist: pyproject-parser (>=0.13.0,<0.14.0)
Requires-Dist: rdflib (>=7.1.4,<8.0.0)
Requires-Dist: typer (>=0.16.0,<0.17.0)
Project-URL: Bug Tracker, https://github.com/white-gecko/doapetry/issues
Project-URL: Homepage, https://github.com/white-gecko/doapetry
Project-URL: Repository, https://github.com/white-gecko/doapetry.git
